hsmm_mvpy/setup.py
hsmm_mvpy-0.3.1.1.dist-info/LICENSE.md
hsmm_mvpy-0.3.1.1.dist-info/METADATA
hsmm_mvpy-0.3.1.1.dist-info/WHEEL
hsmm_mvpy-0.3.1.1.dist-info/top_level.txt
hsmm_mvpy-0.3.1.1.dist-info/RECORD
