Metadata-Version: 2.1
Name: hsmm_mvpy
Version: 0.3.1.1
Summary: DEPRECATED new name under HMP, see https://pypi.org/project/hmp/
Author-email: Gabriel Weindel <gabriel.weindel@gmail.com>, Leendert van Maanen <e@mail.com>, Jelmer Borst <e@mail.com>
License: BSD 3-Clause License
Project-URL: Homepage, https://github.com/GWeindel/hsmm_mvpy
Project-URL: Bug Tracker, https://github.com/GWeindel/hsmm_mvpy/issues
Classifier: Programming Language :: Python :: 3
Classifier: Operating System :: OS Independent
Requires-Python: >=3.10
License-File: LICENSE.md
Requires-Dist: mne >=1.0.0
Requires-Dist: numpy
Requires-Dist: xarray >=2023.8.0
Requires-Dist: scikit-learn
Requires-Dist: statsmodels
Requires-Dist: seaborn
Requires-Dist: scipy
Requires-Dist: netcdf4
Requires-Dist: more-itertools
Requires-Dist: ipywidgets
